README.md
setup.py
pyckage_example_project/__init__.py
pyckage_example_project/main.py
pyckage_example_project.egg-info/PKG-INFO
pyckage_example_project.egg-info/SOURCES.txt
pyckage_example_project.egg-info/dependency_links.txt
pyckage_example_project.egg-info/top_level.txt