Metadata-Version: 2.1
Name: pyckage-example-project
Version: 0.0.1
Summary: a example of what pyckage can generate
Home-page: https://github.com/Madoshakalaka/pyckage-example-project
Author: Matt Yan
Author-email: syan4@ualberta.ca
License: UNKNOWN
Project-URL: Bug Reports, https://github.com/Madoshakalaka/pyckage-example-project/issues
Project-URL: Funding, https://github.com/Madoshakalaka/pyckage-example-project
Project-URL: Say Thanks!, https://github.com/Madoshakalaka/pyckage-example-project
Project-URL: Source, https://github.com/Madoshakalaka/pyckage-example-project
Platform: UNKNOWN
Classifier: Development Status :: 3 - Alpha
Classifier: Intended Audience :: Developers
Classifier: Topic :: Software Development :: Build Tools
Classifier: License :: OSI Approved :: MIT License
Classifier: Programming Language :: Python :: 3.5
Classifier: Programming Language :: Python :: 3.6
Classifier: Programming Language :: Python :: 3.7
Requires-Python: >3.4,  <3.8
